gitai/__init__.py
gitai/agent.py
gitai/main.py
gitai/tools.py
gitai-0.1.16.dist-info/METADATA
gitai-0.1.16.dist-info/WHEEL
gitai-0.1.16.dist-info/entry_points.txt
gitai-0.1.16.dist-info/top_level.txt
gitai-0.1.16.dist-info/RECORD
