Metadata-Version: 2.1
Name: gitai
Version: 0.1.16
Requires-Dist: langchain
Requires-Dist: python-dotenv
Requires-Dist: click
Requires-Dist: langchain-openai
Requires-Dist: langchainhub
Requires-Dist: asyncio
